{
    "homepage": "https://vivaldi.com/",
    "description": "An innovatively designed web browser, based on Blink, for users in Vivaldi.net community that replaced departed My Opera",
    "version": "7.1.3571.3",
    "license": "https://vivaldi.com/privacy/vivaldi-end-user-license-agreement/",
    "architecture": {
        "64bit": {
            "url": "https://downloads.vivaldi.com/snapshot/Vivaldi.7.1.3571.3_arm64-v8a.apk",
            "hash": "37489a66373593b743ef81a492a51b81c22ce5ba6fbd040da763f2fba6e46dc2"
        }
    },
    "checkver": {
        "url": "https://vivaldi.com/blog/feed/",
        "regex": "snapshot/Vivaldi.([\\d.]+)_arm64-v8a.apk"
    },
    "autoupdate": {
        "architecture": {
            "64bit": {
                "url": "https://downloads.vivaldi.com/snapshot/Vivaldi.$version_arm64-v8a.apk"
            }
        }
    }
}
